best/__init__.py
best/integration/__init__.py
best/unit/__init__.py
best/unit/conftest.py
best/unit/test_glue_session.py
best/unit/test_glue_session_demo.py
best/unit/test_session_apis.py
codetf-19.4.6.dist-info/LICENSE.txt
codetf-19.4.6.dist-info/METADATA
codetf-19.4.6.dist-info/WHEEL
codetf-19.4.6.dist-info/top_level.txt
codetf-19.4.6.dist-info/RECORD
